winipyside/__init__.py
winipyside/dev/__init__.py
winipyside/dev/builders/__init__.py
winipyside/dev/cli/__init__.py
winipyside/dev/cli/shared_subcommands.py
winipyside/dev/cli/subcommands.py
winipyside/dev/configs/__init__.py
winipyside/dev/configs/configs.py
winipyside/dev/management/__init__.py
winipyside/dev/tests/__init__.py
winipyside/dev/tests/fixtures/__init__.py
winipyside/main.py
winipyside/py.typed
winipyside/resources/__init__.py
winipyside/resources/delete_garbage_can.svg
winipyside/resources/download_arrow.svg
winipyside/resources/exit_fullscreen_icon.svg
winipyside/resources/fullscreen_icon.svg
winipyside/resources/menu_icon.svg
winipyside/resources/pause_icon.svg
winipyside/resources/play_icon.svg
winipyside/resources/plus_icon.svg
winipyside/src/__init__.py
winipyside/src/core/__init__.py
winipyside/src/core/py_qiodevice.py
winipyside/src/ui/__init__.py
winipyside/src/ui/base/__init__.py
winipyside/src/ui/base/base.py
winipyside/src/ui/pages/__init__.py
winipyside/src/ui/pages/base/__init__.py
winipyside/src/ui/pages/base/base.py
winipyside/src/ui/pages/browser.py
winipyside/src/ui/pages/player.py
winipyside/src/ui/widgets/__init__.py
winipyside/src/ui/widgets/browser.py
winipyside/src/ui/widgets/clickable_widget.py
winipyside/src/ui/widgets/media_player.py
winipyside/src/ui/widgets/notification.py
winipyside/src/ui/windows/__init__.py
winipyside/src/ui/windows/base/__init__.py
winipyside/src/ui/windows/base/base.py
winipyside-2.1.68.dist-info/licenses/LICENSE
winipyside-2.1.68.dist-info/WHEEL
winipyside-2.1.68.dist-info/entry_points.txt
winipyside-2.1.68.dist-info/METADATA
winipyside-2.1.68.dist-info/RECORD
