Metadata-Version: 2.4
Name: winipyside
Version: 2.1.68
Summary: A utilities package for PySide6
Keywords: 
Author: Winipedia
License-Expression: MIT
License-File: LICENSE
Classifier: Programming Language :: Python :: 3.12
Classifier: Programming Language :: Python :: 3.13
Classifier: Operating System :: OS Independent
Classifier: Typing :: Typed
Requires-Dist: pyqt-toast-notification
Requires-Dist: pyside6
Requires-Dist: winiutils
Maintainer: Winipedia
Requires-Python: >=3.12, <3.14
Project-URL: Changelog, https://github.com/Winipedia/winipyside/releases
Project-URL: Documentation, https://Winipedia.github.io/winipyside
Project-URL: Homepage, https://github.com/Winipedia/winipyside
Project-URL: Issues, https://github.com/Winipedia/winipyside/issues
Project-URL: Source, https://github.com/Winipedia/winipyside
